flog_otlp/__init__.py
flog_otlp/cli.py
flog_otlp/logging_config.py
flog_otlp/parser.py
flog_otlp/scenario.py
flog_otlp/sender.py
flog_otlp-0.2.4.dist-info/METADATA
flog_otlp-0.2.4.dist-info/WHEEL
flog_otlp-0.2.4.dist-info/entry_points.txt
flog_otlp-0.2.4.dist-info/licenses/LICENSE
flog_otlp-0.2.4.dist-info/RECORD
