Metadata-Version: 2.4
Name: flog-otlp
Version: 0.2.4
Summary: A Python utility that generates realistic log data using flog and sends it to OpenTelemetry Protocol (OTLP) endpoints or Sumo Logic HTTP sources
Project-URL: Homepage, https://github.com/rjury-sumo/flog_otlp/
Project-URL: Repository, https://github.com/rjury-sumo/flog_otlp.git
Project-URL: Issues, https://github.com/rjury-sumo/flog_otlp/issues
Author-email: Rick Jury <rjury@sumologic.com>
License: MIT License
License-File: LICENSE
Keywords: flog,http-source,logging,observability,opentelemetry,otlp,sumologic,testing
Classifier: Development Status :: 3 - Alpha
Classifier: Intended Audience :: Developers
Classifier: License :: OSI Approved :: MIT License
Classifier: Programming Language :: Python :: 3
Classifier: Programming Language :: Python :: 3.12
Classifier: Programming Language :: Python :: 3.13
Classifier: Topic :: System :: Logging
Classifier: Topic :: System :: Monitoring
Requires-Python: >=3.13
Requires-Dist: lorem-text>=2.1.0
Requires-Dist: pyyaml>=6.0.0
Requires-Dist: requests>=2.25.0
